testkitllm-0.2.0.dist-info/licenses/LICENSE
testllm/__init__.py
testllm/__version__.py
testllm/assertions.py
testllm/auth.py
testllm/behavioral.py
testllm/config.py
testllm/core.py
testllm/credentials.py
testllm/evaluation_loop.py
testllm/flows.py
testllm/pytest_plugin.py
testllm/pytest_semantic.py
testllm/reporting.py
testllm/semantic.py
testllm/setup.py
testllm/telemetry.py
testllm/tool_testing/__init__.py
testllm/tool_testing/adapters.py
testllm/tool_testing/expectations.py
testllm/tool_testing/interceptor.py
testllm/tool_testing/scenarios.py
testllm/tool_testing/simulation.py
testllm/tool_testing/types.py
testkitllm-0.2.0.dist-info/METADATA
testkitllm-0.2.0.dist-info/WHEEL
testkitllm-0.2.0.dist-info/entry_points.txt
testkitllm-0.2.0.dist-info/top_level.txt
testkitllm-0.2.0.dist-info/RECORD
