Metadata-Version: 2.4
Name: testkitLLM
Version: 0.2.0
Summary: Testing Framework for LLM-Based Agents
Home-page: https://github.com/rcgalbo/wayy-research
Author: testLLM Team
Author-email: rcgalbo@gmail.com
Project-URL: Bug Tracker, https://github.com/rcgalbo/wayy-research/issues
Project-URL: Documentation, https://github.com/rcgalbo/wayy-research/blob/main/README.md
Project-URL: Source Code, https://github.com/rcgalbo/wayy-research
Keywords: testing llm agents ai machine-learning pytest
Classifier: Development Status :: 4 - Beta
Classifier: Intended Audience :: Developers
Classifier: Topic :: Software Development :: Testing
Classifier: Topic :: Scientific/Engineering :: Artificial Intelligence
Classifier: License :: Other/Proprietary License
Classifier: Programming Language :: Python :: 3
Classifier: Programming Language :: Python :: 3.9
Classifier: Programming Language :: Python :: 3.10
Classifier: Programming Language :: Python :: 3.11
Classifier: Programming Language :: Python :: 3.12
Classifier: Operating System :: OS Independent
Requires-Python: >=3.9
License-File: LICENSE
Requires-Dist: pytest>=7.0.0
Requires-Dist: PyYAML>=6.0
Requires-Dist: requests>=2.25.0
Requires-Dist: python-dotenv>=0.19.0
Provides-Extra: dev
Requires-Dist: pytest-cov>=4.0.0; extra == "dev"
Requires-Dist: black>=22.0.0; extra == "dev"
Requires-Dist: flake8>=5.0.0; extra == "dev"
Requires-Dist: mypy>=1.0.0; extra == "dev"
Requires-Dist: twine>=4.0.0; extra == "dev"
Requires-Dist: build>=0.10.0; extra == "dev"
Provides-Extra: test
Requires-Dist: pytest-xdist>=3.0.0; extra == "test"
Requires-Dist: pytest-mock>=3.10.0; extra == "test"
Requires-Dist: responses>=0.23.0; extra == "test"
Dynamic: author
Dynamic: author-email
Dynamic: classifier
Dynamic: description
Dynamic: description-content-type
Dynamic: home-page
Dynamic: keywords
Dynamic: license-file
Dynamic: project-url
Dynamic: provides-extra
Dynamic: requires-dist
Dynamic: requires-python
Dynamic: summary
